flowalign/__init__.py
flowalign/__main__.py
flowalign/_version.py
flowalign/flowaligner.py
flowalign/functions_based_on_sam_2_fasta.py
flowalign/helpers.py
flowalign/test_fasta_files_are_identical.py
flowalign-0.11.dist-info/METADATA
flowalign-0.11.dist-info/WHEEL
flowalign-0.11.dist-info/entry_points.txt
flowalign-0.11.dist-info/top_level.txt
flowalign-0.11.dist-info/RECORD
