Metadata-Version: 2.1
Name: flowalign
Version: 0.11
Summary: Alignment generator using mappy and Python
Home-page: https://github.com/theosanderson/flowalign
Author: Theo Sanderson
Author-email: theo@theo.io
Project-URL: Bug Tracker, https://github.com/theosanderson/flowalign/issues
Classifier: Programming Language :: Python :: 3
Classifier: License :: OSI Approved :: MIT License
Classifier: Operating System :: OS Independent
Requires-Python: >=3.6
Requires-Dist: mappy (==2.22)
Requires-Dist: tqdm
